openmodule/__init__.py
openmodule/alert.py
openmodule/config.py
openmodule/connection_status.py
openmodule/core.py
openmodule/dispatcher.py
openmodule/health.py
openmodule/logging.py
openmodule/messaging.py
openmodule/sentry.py
openmodule/threading.py
openmodule/database/__init__.py
openmodule/database/custom_types.py
openmodule/database/database.py
openmodule/database/env.py
openmodule/database/migration.py
openmodule/models/__init__.py
openmodule/models/access_service.py
openmodule/models/alert.py
openmodule/models/base.py
openmodule/models/io.py
openmodule/models/kv_store.py
openmodule/models/presence.py
openmodule/models/privacy.py
openmodule/models/rpc.py
openmodule/models/settings.py
openmodule/models/signals.py
openmodule/models/validation.py
openmodule/models/vehicle.py
openmodule/rpc/__init__.py
openmodule/rpc/client.py
openmodule/rpc/common.py
openmodule/rpc/server.py
openmodule/utils/__init__.py
openmodule/utils/access_service.py
openmodule/utils/charset.py
openmodule/utils/cleanup.py
openmodule/utils/csv_export.py
openmodule/utils/databox.py
openmodule/utils/db_helper.py
openmodule/utils/eventlog.py
openmodule/utils/io.py
openmodule/utils/kv_store.py
openmodule/utils/matching.py
openmodule/utils/misc_functions.py
openmodule/utils/package_reader.py
openmodule/utils/presence.py
openmodule/utils/schedule.py
openmodule/utils/settings.py
openmodule/utils/signal_listener.py
openmodule/utils/translation.py
openmodule/utils/validation.py
openmodule-16.0.5.dist-info/licenses/LICENSE
openmodule-16.0.5.dist-info/METADATA
openmodule-16.0.5.dist-info/WHEEL
openmodule-16.0.5.dist-info/top_level.txt
openmodule-16.0.5.dist-info/RECORD
