Metadata-Version: 2.4
Name: openmodule
Version: 16.0.5
Summary: Libraries for developing the arivo openmodule
Home-page: https://gitlab.com/arivo-public/device-python/openmodule.git
Author: ARIVO
Author-email: support@arivo.co
License: GNU General Public License v2 (GPLv2)
Keywords: arivo openmodule
Classifier: Intended Audience :: Developers
Classifier: License :: OSI Approved :: GNU General Public License v2 (GPLv2)
Classifier: Programming Language :: Python
Classifier: Programming Language :: Python :: 3.12
License-File: LICENSE
Requires-Dist: pydantic~=2.0
Requires-Dist: sentry-sdk~=2.19.0
Requires-Dist: orjson<4,>=3.4.7
Requires-Dist: pyzmq~=26.2
Requires-Dist: pyyaml<7,>=5.0
Requires-Dist: editdistance>=0.8.1
Requires-Dist: sqlalchemy~=2.0.0
Requires-Dist: alembic<2,>=1.5.4
Requires-Dist: requests<3,>=2.22
Requires-Dist: python-dateutil>=2.7.2
Requires-Dist: python-dotenv~=0.15
Requires-Dist: arivo-settings_models<3,>=2.4.5
Provides-Extra: test
Requires-Dist: openmodule_test; extra == "test"
Provides-Extra: commands
Requires-Dist: openmodule_commands; extra == "commands"
Dynamic: author
Dynamic: author-email
Dynamic: classifier
Dynamic: description
Dynamic: description-content-type
Dynamic: home-page
Dynamic: keywords
Dynamic: license
Dynamic: license-file
Dynamic: provides-extra
Dynamic: requires-dist
Dynamic: summary
